robinhood_commons/__init__.py
robinhood_commons/dao/__init__.py
robinhood_commons/dao/robinhood_base_dao.py
robinhood_commons/dao/stock_dao.py
robinhood_commons/dao/user_dao.py
robinhood_commons/dao/impl/__init__.py
robinhood_commons/dao/impl/stock_dao_impl.py
robinhood_commons/entity/__init__.py
robinhood_commons/entity/aggregate_position.py
robinhood_commons/entity/auth_info.py
robinhood_commons/entity/candle.py
robinhood_commons/entity/cash_type.py
robinhood_commons/entity/chain.py
robinhood_commons/entity/direction.py
robinhood_commons/entity/dividend.py
robinhood_commons/entity/earnings.py
robinhood_commons/entity/effect.py
robinhood_commons/entity/execution_request.py
robinhood_commons/entity/execution_result.py
robinhood_commons/entity/execution_type.py
robinhood_commons/entity/fundamentals.py
robinhood_commons/entity/historicals.py
robinhood_commons/entity/history.py
robinhood_commons/entity/investor.py
robinhood_commons/entity/investor_stats.py
robinhood_commons/entity/lot.py
robinhood_commons/entity/market.py
robinhood_commons/entity/mover.py
robinhood_commons/entity/news.py
robinhood_commons/entity/offer.py
robinhood_commons/entity/option.py
robinhood_commons/entity/option_type.py
robinhood_commons/entity/order.py
robinhood_commons/entity/popularity.py
robinhood_commons/entity/portfolio.py
robinhood_commons/entity/position.py
robinhood_commons/entity/price.py
robinhood_commons/entity/printable.py
robinhood_commons/entity/quote.py
robinhood_commons/entity/ratings.py
robinhood_commons/entity/stat_type.py
robinhood_commons/entity/state.py
robinhood_commons/entity/stock.py
robinhood_commons/entity/strategy_decision.py
robinhood_commons/entity/tick.py
robinhood_commons/entity/time_in_force.py
robinhood_commons/entity/tradability.py
robinhood_commons/entity/transfer.py
robinhood_commons/entity/user.py
robinhood_commons/entity/order_type/__init__.py
robinhood_commons/entity/order_type/limit_order_request.py
robinhood_commons/entity/order_type/order_request.py
robinhood_commons-1.0.40.dist-info/METADATA
robinhood_commons-1.0.40.dist-info/WHEEL
robinhood_commons-1.0.40.dist-info/top_level.txt
robinhood_commons-1.0.40.dist-info/RECORD
