Metadata-Version: 2.1
Name: robinhood-commons
Version: 1.0.40
Summary: Robinhood DayTrader Commons
Home-page: https://github.com/mhowell234/robinhood_commons
Author: mhowell234
Author-email: mhowell234@gmail.com
License: UNKNOWN
Platform: UNKNOWN
Classifier: Development Status :: 3 - Alpha
Classifier: Programming Language :: Python :: 3.8
Requires: pyotp
Requires: requests
Requires: robin_stocks
Requires-Python: >=3.8, <4
Requires-Dist: pyotp
Requires-Dist: requests
Requires-Dist: robin-stocks
